jetline/__init__.py
jetline/logging.py
jetline/commands/__init__.py
jetline/commands/_helper.py
jetline/commands/create_pipe.py
jetline/commands/create_viz.py
jetline/commands/info.py
jetline/commands/installer.py
jetline/commands/run_pipeline.py
jetline/commands/to_exe.py
jetline/data/__init__.py
jetline/data/data.py
jetline/data/helper.py
jetline/pipeline/__init__.py
jetline/pipeline/node.py
jetline/pipeline/pipeline.py
jetline/templates/__init__.py
jetline/templates/data.py
jetline/templates/main.py
jetline/templates/nodes.py
jetline/templates/pipeline.py
jetline/visualization/__init__.py
jetline/visualization/server/.DS_Store
jetline/visualization/server/__init__.py
jetline/visualization/server/server.py
jetline/visualization/server/dist/index.html
jetline/visualization/server/dist/vite.svg
jetline/visualization/server/dist/assets/index-BCqVGvry.js
jetline/visualization/server/dist/assets/index-BUXWNTAg.css
jetline/visualization/server/dist/assets/assets/index-BCqVGvry.js
jetline/visualization/server/dist/assets/assets/index-BUXWNTAg.css
jetline-1.0.1.dist-info/METADATA
jetline-1.0.1.dist-info/WHEEL
jetline-1.0.1.dist-info/entry_points.txt
jetline-1.0.1.dist-info/top_level.txt
jetline-1.0.1.dist-info/RECORD
