Metadata-Version: 2.1
Name: jetline
Version: 1.0.1
Summary: Automated Pipeline Builder
Home-page: https://github.com/your_username/jetline
Author: Johannes Kanthak
Author-email: johannes.kanthak@kdc-solutions.de
License: MIT
Classifier: Development Status :: 3 - Alpha
Classifier: Intended Audience :: Developers
Classifier: License :: OSI Approved :: MIT License
Classifier: Operating System :: OS Independent
Classifier: Programming Language :: Python :: 3
Classifier: Programming Language :: Python :: 3.6
Classifier: Programming Language :: Python :: 3.7
Classifier: Programming Language :: Python :: 3.8
Classifier: Programming Language :: Python :: 3.9
Classifier: Programming Language :: Python :: 3.10
Classifier: Topic :: Software Development :: Libraries :: Python Modules
Requires-Dist: toml ~=0.10.2
Requires-Dist: jetline ~=0.1.4
Requires-Dist: pandas ~=2.2.0
Requires-Dist: click ~=8.1.7
Requires-Dist: colorama ~=0.4.6
Requires-Dist: coloredlogs ~=15.0.1
Requires-Dist: loguru ~=0.7.2
Requires-Dist: fastapi ~=0.110.0
Requires-Dist: vulture ~=2.11
Requires-Dist: astor ~=0.8.1
Requires-Dist: setuptools ~=69.5.1
Requires-Dist: flaskwebgui ~=1.1.1
Requires-Dist: uvicorn ~=0.29.0
